CITATION
COPYING.txt
MANIFEST.in
README.md
setup.py
thingking/__init__.py
thingking/arbitrary_page.py
thingking/httpmmap.py
thingking/utils.py
thingking.egg-info/PKG-INFO
thingking.egg-info/SOURCES.txt
thingking.egg-info/dependency_links.txt
thingking.egg-info/requires.txt
thingking.egg-info/top_level.txt