Metadata-Version: 1.1
Name: thingking
Version: 1.0.1
Summary: A memory map for the World Wide Web
Home-page: UNKNOWN
Author: Matthew Turk <matthewturk@gmail.com>, Samuel Skillman <samskillman@gmail.com>, Michael S. Warren <mswarren@gmail.com>
Author-email: UNKNOWN
License: BSD
Keywords: data
Platform: UNKNOWN
Classifier: Programming Language :: Python
Classifier: Topic :: Software Development :: Libraries :: Python Modules
